README.rst
setup.py
fixeddatatable/__init__.py
fixeddatatable/core.py
fixeddatatable.egg-info/PKG-INFO
fixeddatatable.egg-info/SOURCES.txt
fixeddatatable.egg-info/dependency_links.txt
fixeddatatable.egg-info/top_level.txt