Metadata-Version: 1.1
Name: fixeddatatable
Version: 0.0.1
Summary: Utilities for interfacing with FixedDataTable.js
Home-page: https://github.com/jeffroche/fixed-data-table-py
Author: Jeff Roche
Author-email: jeff.roche@gmail.com
License: MIT
Keywords: js
Platform: UNKNOWN
Classifier: Development Status :: 3 - Alpha
Classifier: Intended Audience :: Developers
Classifier: Topic :: Software Development :: Build Tools
Classifier: License :: OSI Approved :: MIT License
Classifier: Programming Language :: Python :: 2
Classifier: Programming Language :: Python :: 2.6
Classifier: Programming Language :: Python :: 2.7
